{
 "cells": [
  {
   "cell_type": "code",
   "execution_count": 1,
   "metadata": {
    "collapsed": true
   },
   "outputs": [],
   "source": [
    "# Understanding variable scope"
   ]
  },
  {
   "cell_type": "code",
   "execution_count": 2,
   "metadata": {},
   "outputs": [
    {
     "name": "stdout",
     "output_type": "stream",
     "text": [
      "3\n"
     ]
    },
    {
     "ename": "NameError",
     "evalue": "name 'b' is not defined",
     "traceback": [
      "\u001b[0;31m---------------------------------------------------------------------------\u001b[0m",
      "\u001b[0;31mNameError\u001b[0m                                 Traceback (most recent call last)",
      "\u001b[0;32m<ipython-input-2-009ad9378744>\u001b[0m in \u001b[0;36m<module>\u001b[0;34m()\u001b[0m\n\u001b[1;32m      3\u001b[0m     \u001b[0mprint\u001b[0m\u001b[0;34m(\u001b[0m\u001b[0mb\u001b[0m\u001b[0;34m)\u001b[0m\u001b[0;34m\u001b[0m\u001b[0m\n\u001b[1;32m      4\u001b[0m \u001b[0;34m\u001b[0m\u001b[0m\n\u001b[0;32m----> 5\u001b[0;31m \u001b[0mf1\u001b[0m\u001b[0;34m(\u001b[0m\u001b[0;36m3\u001b[0m\u001b[0;34m)\u001b[0m\u001b[0;34m\u001b[0m\u001b[0m\n\u001b[0m",
      "\u001b[0;32m<ipython-input-2-009ad9378744>\u001b[0m in \u001b[0;36mf1\u001b[0;34m(a)\u001b[0m\n\u001b[1;32m      1\u001b[0m \u001b[0;32mdef\u001b[0m \u001b[0mf1\u001b[0m\u001b[0;34m(\u001b[0m\u001b[0ma\u001b[0m\u001b[0;34m)\u001b[0m\u001b[0;34m:\u001b[0m\u001b[0;34m\u001b[0m\u001b[0m\n\u001b[1;32m      2\u001b[0m     \u001b[0mprint\u001b[0m\u001b[0;34m(\u001b[0m\u001b[0ma\u001b[0m\u001b[0;34m)\u001b[0m\u001b[0;34m\u001b[0m\u001b[0m\n\u001b[0;32m----> 3\u001b[0;31m     \u001b[0mprint\u001b[0m\u001b[0;34m(\u001b[0m\u001b[0mb\u001b[0m\u001b[0;34m)\u001b[0m\u001b[0;34m\u001b[0m\u001b[0m\n\u001b[0m\u001b[1;32m      4\u001b[0m \u001b[0;34m\u001b[0m\u001b[0m\n\u001b[1;32m      5\u001b[0m \u001b[0mf1\u001b[0m\u001b[0;34m(\u001b[0m\u001b[0;36m3\u001b[0m\u001b[0;34m)\u001b[0m\u001b[0;34m\u001b[0m\u001b[0m\n",
      "\u001b[0;31mNameError\u001b[0m: name 'b' is not defined"
     ],
     "output_type": "error"
    }
   ],
   "source": [
    "def f1(a):\n",
    "    print(a)\n",
    "    print(b)\n",
    "\n",
    "f1(3)"
   ]
  },
  {
   "cell_type": "code",
   "execution_count": 3,
   "metadata": {},
   "outputs": [
    {
     "name": "stdout",
     "output_type": "stream",
     "text": [
      "30\n3\n"
     ]
    }
   ],
   "source": [
    "b = 3\n",
    "f1(30)"
   ]
  },
  {
   "cell_type": "code",
   "execution_count": null,
   "metadata": {},
   "outputs": [],
   "source": [
    "# Not surprisingly it searched for b in local scope didn't find it\n",
    "# and looked in global LEGB"
   ]
  },
  {
   "cell_type": "code",
   "execution_count": 4,
   "metadata": {},
   "outputs": [
    {
     "name": "stdout",
     "output_type": "stream",
     "text": [
      "3\n"
     ]
    },
    {
     "ename": "UnboundLocalError",
     "evalue": "local variable 'b' referenced before assignment",
     "traceback": [
      "\u001b[0;31m---------------------------------------------------------------------------\u001b[0m",
      "\u001b[0;31mUnboundLocalError\u001b[0m                         Traceback (most recent call last)",
      "\u001b[0;32m<ipython-input-4-e66a06b6a313>\u001b[0m in \u001b[0;36m<module>\u001b[0;34m()\u001b[0m\n\u001b[1;32m      6\u001b[0m     \u001b[0mb\u001b[0m \u001b[0;34m=\u001b[0m \u001b[0;36m9\u001b[0m\u001b[0;34m\u001b[0m\u001b[0m\n\u001b[1;32m      7\u001b[0m \u001b[0;34m\u001b[0m\u001b[0m\n\u001b[0;32m----> 8\u001b[0;31m \u001b[0mf2\u001b[0m\u001b[0;34m(\u001b[0m\u001b[0;36m3\u001b[0m\u001b[0;34m)\u001b[0m\u001b[0;34m\u001b[0m\u001b[0m\n\u001b[0m",
      "\u001b[0;32m<ipython-input-4-e66a06b6a313>\u001b[0m in \u001b[0;36mf2\u001b[0;34m(a)\u001b[0m\n\u001b[1;32m      3\u001b[0m \u001b[0;32mdef\u001b[0m \u001b[0mf2\u001b[0m\u001b[0;34m(\u001b[0m\u001b[0ma\u001b[0m\u001b[0;34m)\u001b[0m\u001b[0;34m:\u001b[0m\u001b[0;34m\u001b[0m\u001b[0m\n\u001b[1;32m      4\u001b[0m     \u001b[0mprint\u001b[0m\u001b[0;34m(\u001b[0m\u001b[0ma\u001b[0m\u001b[0;34m)\u001b[0m\u001b[0;34m\u001b[0m\u001b[0m\n\u001b[0;32m----> 5\u001b[0;31m     \u001b[0mprint\u001b[0m\u001b[0;34m(\u001b[0m\u001b[0mb\u001b[0m\u001b[0;34m)\u001b[0m\u001b[0;34m\u001b[0m\u001b[0m\n\u001b[0m\u001b[1;32m      6\u001b[0m     \u001b[0mb\u001b[0m \u001b[0;34m=\u001b[0m \u001b[0;36m9\u001b[0m\u001b[0;34m\u001b[0m\u001b[0m\n\u001b[1;32m      7\u001b[0m \u001b[0;34m\u001b[0m\u001b[0m\n",
      "\u001b[0;31mUnboundLocalError\u001b[0m: local variable 'b' referenced before assignment"
     ],
     "output_type": "error"
    }
   ],
   "source": [
    "b = 6\n",
    "\n",
    "def f2(a):\n",
    "    print(a)\n",
    "    print(b)\n",
    "    b = 9\n",
    "\n",
    "f2(3)"
   ]
  },
  {
   "cell_type": "code",
   "execution_count": null,
   "metadata": {},
   "outputs": [],
   "source": [
    "# When python compiles the body of this function it decides\n",
    "# That b is a local variable because it is assigned within\n",
    "# the function. Later when the call f2(3) is made, the body of\n",
    "# f2 fetches and print value of local variable a, but then\n",
    "# when trying to fetch the value of local variable b it discovers\n",
    "# b is unbound\n",
    "\n",
    "# This is  a design choice, Python doesn't require you to \n",
    "# declare variables, but assumes that a variable assigned in the \n",
    "# body of function is local"
   ]
  },
  {
   "cell_type": "code",
   "execution_count": 6,
   "metadata": {},
   "outputs": [
    {
     "name": "stdout",
     "output_type": "stream",
     "text": [
      "3\n6\n"
     ]
    }
   ],
   "source": [
    "def f3(a):\n",
    "    \"\"\"To override this behaviour use global\"\"\"\n",
    "    global b\n",
    "    print(a)\n",
    "    print(b)\n",
    "    b = 9\n",
    "\n",
    "f3(3)"
   ]
  },
  {
   "cell_type": "code",
   "execution_count": 7,
   "metadata": {},
   "outputs": [
    {
     "data": {
      "text/plain": [
       "9"
      ]
     },
     "execution_count": 7,
     "metadata": {},
     "output_type": "execute_result"
    }
   ],
   "source": [
    "b"
   ]
  },
  {
   "cell_type": "code",
   "execution_count": 10,
   "metadata": {},
   "outputs": [
    {
     "name": "stdout",
     "output_type": "stream",
     "text": [
      "  2           0 LOAD_GLOBAL              0 (print)\n              2 LOAD_FAST                0 (a)\n              4 CALL_FUNCTION            1\n              6 POP_TOP\n\n  3           8 LOAD_GLOBAL              0 (print)\n             10 LOAD_GLOBAL              1 (b)\n             12 CALL_FUNCTION            1\n             14 POP_TOP\n             16 LOAD_CONST               0 (None)\n             18 RETURN_VALUE\n"
     ]
    }
   ],
   "source": [
    "from dis import dis\n",
    "dis(f1)"
   ]
  },
  {
   "cell_type": "code",
   "execution_count": 11,
   "metadata": {},
   "outputs": [
    {
     "name": "stdout",
     "output_type": "stream",
     "text": [
      "  4           0 LOAD_GLOBAL              0 (print)\n              2 LOAD_FAST                0 (a)\n              4 CALL_FUNCTION            1\n              6 POP_TOP\n\n  5           8 LOAD_GLOBAL              0 (print)\n             10 LOAD_FAST                1 (b)\n             12 CALL_FUNCTION            1\n             14 POP_TOP\n\n  6          16 LOAD_CONST               1 (9)\n             18 STORE_FAST               1 (b)\n             20 LOAD_CONST               0 (None)\n             22 RETURN_VALUE\n"
     ]
    }
   ],
   "source": [
    "dis(f2)"
   ]
  },
  {
   "cell_type": "code",
   "execution_count": 12,
   "metadata": {},
   "outputs": [
    {
     "name": "stdout",
     "output_type": "stream",
     "text": [
      "  4           0 LOAD_GLOBAL              0 (print)\n              2 LOAD_FAST                0 (a)\n              4 CALL_FUNCTION            1\n              6 POP_TOP\n\n  5           8 LOAD_GLOBAL              0 (print)\n             10 LOAD_GLOBAL              1 (b)\n             12 CALL_FUNCTION            1\n             14 POP_TOP\n\n  6          16 LOAD_CONST               1 (9)\n             18 STORE_GLOBAL             1 (b)\n             20 LOAD_CONST               2 (None)\n             22 RETURN_VALUE\n"
     ]
    }
   ],
   "source": [
    "dis(f3)"
   ]
  }
 ],
 "metadata": {
  "kernelspec": {
   "display_name": "Python 2",
   "language": "python",
   "name": "python2"
  },
  "language_info": {
   "codemirror_mode": {
    "name": "ipython",
    "version": 2.0
   },
   "file_extension": ".py",
   "mimetype": "text/x-python",
   "name": "python",
   "nbconvert_exporter": "python",
   "pygments_lexer": "ipython2",
   "version": "2.7.6"
  }
 },
 "nbformat": 4,
 "nbformat_minor": 0
}